setup.py
dvadeus_probability/Binomialdistribution.py
dvadeus_probability/Gaussiandistribution.py
dvadeus_probability/Generaldistribution.py
dvadeus_probability/__init__.py
dvadeus_probability.egg-info/PKG-INFO
dvadeus_probability.egg-info/SOURCES.txt
dvadeus_probability.egg-info/dependency_links.txt
dvadeus_probability.egg-info/not-zip-safe
dvadeus_probability.egg-info/top_level.txt