Metadata-Version: 2.1
Name: dvadeus-probability
Version: 0.2
Summary: Gaussian snd Binomial distributions
Author-email: email@email.com
